{
  "total_trades": 4,
  "winners": 1,
  "losers": 3,
  "win_rate": 25.0,
  "profit_factor": 0.6,
  "total_pnl": -800.0,
  "avg_pnl": -200.0,
  "avg_winner": 1205.0,
  "avg_loser": 668.33,
  "sharpe_ratio": -5.38,
  "max_drawdown": 555.0,
  "exit_reasons": {
    "BIG_RED_CANDLE": 2,
    "TRAILING_SL": 1,
    "TIME_EXIT": 1
  },
  "symbol_stats": {
    "('pnl', 'count')": {
      "TCS": 2,
      "ULTRACEMCO": 1,
      "WIPRO": 1
    },
    "('pnl', 'sum')": {
      "TCS": -2005.0,
      "ULTRACEMCO": 1205.0,
      "WIPRO": 0.0
    },
    "('pnl', 'mean')": {
      "TCS": -1002.5,
      "ULTRACEMCO": 1205.0,
      "WIPRO": 0.0
    },
    "('pnl_pct', 'mean')": {
      "TCS": -6.57,
      "ULTRACEMCO": 4.77,
      "WIPRO": 0.0
    }
  },
  "trades": [
    {
      "symbol": "TCS",
      "entry_time": "2024-11-06 04:48:00+00:00",
      "exit_time": "2024-11-06 05:00:00+00:00",
      "entry_price": 4091.25,
      "exit_price": 4075.5,
      "pnl": -1450.0,
      "pnl_pct": -9.945130315500684,
      "exit_reason": "BIG_RED_CANDLE"
    },
    {
      "symbol": "TCS",
      "entry_time": "2024-11-22 04:46:00+00:00",
      "exit_time": "2024-11-22 04:52:00+00:00",
      "entry_price": 4137.05,
      "exit_price": 4133.15,
      "pnl": -554.9999999999998,
      "pnl_pct": -3.203463203463202,
      "exit_reason": "BIG_RED_CANDLE"
    },
    {
      "symbol": "WIPRO",
      "entry_time": "2024-11-06 04:48:00+00:00",
      "exit_time": "2024-11-06 04:56:00+00:00",
      "entry_price": 279.6,
      "exit_price": 278.799,
      "pnl": 0.0,
      "pnl_pct": 0.0,
      "exit_reason": "TRAILING_SL"
    },
    {
      "symbol": "ULTRACEMCO",
      "entry_time": "2024-11-06 06:04:00+00:00",
      "exit_time": "2024-11-06 06:30:00+00:00",
      "entry_price": 11195.1,
      "exit_price": 11223.1,
      "pnl": 1205.0000000000011,
      "pnl_pct": 4.771332409423881,
      "exit_reason": "TIME_EXIT"
    }
  ]
}